js_lib_alpinejs/__init__.py
js_lib_alpinejs/apps.py
js_lib_alpinejs/static/js_lib_alpinejs/alpine.js
js_lib_alpinejs/static/js_lib_alpinejs/alpine.min.js
django_js_lib_alpinejs-3.14.7.1.dist-info/LICENSE
django_js_lib_alpinejs-3.14.7.1.dist-info/WHEEL
django_js_lib_alpinejs-3.14.7.1.dist-info/METADATA
django_js_lib_alpinejs-3.14.7.1.dist-info/RECORD
