Metadata-Version: 2.1
Name: django-js-lib-alpinejs
Version: 3.14.7.1
Summary: Alpine.js for Django
Classifier: License :: OSI Approved :: MIT License
